setup.py
./__init__.py
./async.py
./connection.py
./deflate_frame.py
./deflate_message.py
./errors.py
./extension.py
./frame.py
./handshake.py
./message.py
./multiplex.py
./python_digest.py
./server.py
./websocket.py
wspy.egg-info/PKG-INFO
wspy.egg-info/SOURCES.txt
wspy.egg-info/dependency_links.txt
wspy.egg-info/top_level.txt