Metadata-Version: 1.0
Name: wspy
Version: 0.9.1
Summary: A standalone implementation of websockets (RFC 6455).
Home-page: https://github.com/taddeus/wspy
Author: Taddeus Kroes
Author-email: taddeus@kompiler.org
License: 3-clause BSD License
Platform: UNKNOWN
